slide_detector/__init__.py
slide_detector/slide_detector.py
SlideDetector-0.1.0.dist-info/LICENSE.txt
SlideDetector-0.1.0.dist-info/METADATA
SlideDetector-0.1.0.dist-info/WHEEL
SlideDetector-0.1.0.dist-info/entry_points.txt
SlideDetector-0.1.0.dist-info/top_level.txt
SlideDetector-0.1.0.dist-info/RECORD
