Metadata-Version: 2.1
Name: SlideDetector
Version: 0.1.0
Summary: A tool for detecting slide changes in videos and saving them as PowerPoint slides.
Author: gitrandoname
Author-email: 165725564+gitrandoname@users.noreply.github.com
License: GPLv3
Project-URL: Source, https://github.com/gitrandoname/SlideDetect.git
Project-URL: Tracker, https://github.com/gitrandoname/SlideDetect/issues
Keywords: video processing slide detection PowerPoint
Classifier: Development Status :: 4 - Beta
Classifier: Intended Audience :: Developers
Classifier: License :: OSI Approved :: GNU General Public License v3 (GPLv3)
Classifier: Programming Language :: Python :: 3
Classifier: Programming Language :: Python :: 3.6
Classifier: Programming Language :: Python :: 3.7
Classifier: Programming Language :: Python :: 3.8
Classifier: Programming Language :: Python :: 3.9
Classifier: Programming Language :: Python :: 3.10
Requires-Python: >=3.6
License-File: LICENSE.txt
Requires-Dist: opencv-python-headless
Requires-Dist: numpy
Requires-Dist: python-pptx
Requires-Dist: Pillow
Requires-Dist: tqdm
